Metadata-Version: 1.0
Name: pikachuy-groupA
Version: 0.1
Summary: Python Packaging Starting Kit - Simple Structure to creater your own package - for training purposes!
Home-page: https://github.com/manoelgadi/pythonpackagesample
Author: Group A
Author-email: GroupA@student.ie.edu
License: MIT
Platform: UNKNOWN
